anagram/__init__.py
anagram/main.py
pnu_anagram-1.2.2.data/data/man/man6/anagram.6.gz
pnu_anagram-1.2.2.dist-info/License
pnu_anagram-1.2.2.dist-info/METADATA
pnu_anagram-1.2.2.dist-info/WHEEL
pnu_anagram-1.2.2.dist-info/entry_points.txt
pnu_anagram-1.2.2.dist-info/top_level.txt
pnu_anagram-1.2.2.dist-info/RECORD
